
{"Event":{"System":{"Provider":{"@Name":"Microsoft-Windows-Security-Auditing","@Guid":"54849625-5478-4994-a5ba-3e3b0328c30d"},"EventID":"4616","Version":"1","Level":"0","Task":"12288","Opcode":"0","Keywords":"0x8020000000000000","TimeCreated":{"@SystemTime":"2024-10-24 13:19:17.0616986"},"EventRecordID":"30349","Correlation":null,"Execution":{"@ProcessID":"4","@ThreadID":"100"},"Channel":"Security","Computer":"Server002","Security":null},"EventData":{"Data":[{"@Name":"SubjectUserSid","#text":"S-1-5-19"},{"@Name":"SubjectUserName","#text":"LOCAL SERVICE"},{"@Name":"SubjectDomainName","#text":"NT AUTHORITY"},{"@Name":"SubjectLogonId","#text":"0x3E5"},{"@Name":"PreviousTime","#text":"2024-10-24 13:19:22.3066546"},{"@Name":"NewTime","#text":"2024-10-24 13:19:17.0610109"},{"@Name":"ProcessId","#text":"0xEA4"},{"@Name":"ProcessName","#text":"C:\\Windows\\System32\\svchost.exe"}]}}}
{"Event":{"System":{"Provider":{"@Name":"Microsoft-Windows-Security-Auditing","@Guid":"54849625-5478-4994-a5ba-3e3b0328c30d"},"EventID":"4616","Version":"1","Level":"0","Task":"12288","Opcode":"0","Keywords":"0x8020000000000000","TimeCreated":{"@SystemTime":"2024-10-24 13:19:17.0626865"},"EventRecordID":"30350","Correlation":null,"Execution":{"@ProcessID":"4","@ThreadID":"100"},"Channel":"Security","Computer":"Server002","Security":null},"EventData":{"Data":[{"@Name":"SubjectUserSid","#text":"S-1-5-19"},{"@Name":"SubjectUserName","#text":"LOCAL SERVICE"},{"@Name":"SubjectDomainName","#text":"NT AUTHORITY"},{"@Name":"SubjectLogonId","#text":"0x3E5"},{"@Name":"PreviousTime","#text":"2024-10-24 13:19:17.0610109"},{"@Name":"NewTime","#text":"2024-10-24 13:19:17.0622615"},{"@Name":"ProcessId","#text":"0xEA4"},{"@Name":"ProcessName","#text":"C:\\Windows\\System32\\svchost.exe"}]}}}
